enterprise_search/__init__.py
enterprise_search/cli.py
enterprise_search/enterprise_search.py
enterprise_search-0.0.1.dist-info/entry_points.txt
enterprise_search-0.0.1.dist-info/LICENSE
enterprise_search-0.0.1.dist-info/WHEEL
enterprise_search-0.0.1.dist-info/METADATA
enterprise_search-0.0.1.dist-info/RECORD
