Metadata-Version: 2.1
Name: enterprise-search
Version: 0.0.1
Summary: Enterprise search CLI.
Home-page: https://github.com/nsi88/enterprise_search
License: GPL-3.0-only
Author: Sergey Novikov
Author-email: sergey.igorevitch.novikov@gmail.com
Requires-Python: >=3.9,<4.0
Classifier: Development Status :: 2 - Pre-Alpha
Classifier: Intended Audience :: Developers
Classifier: License :: OSI Approved :: GNU General Public License v3 (GPLv3)
Classifier: Natural Language :: English
Classifier: Programming Language :: Python :: 3
Classifier: Programming Language :: Python :: 3.10
Classifier: Programming Language :: Python :: 3.9
Provides-Extra: dev
Provides-Extra: doc
Provides-Extra: test
Requires-Dist: black (>=21.5b2,<22.0); extra == "test"
Requires-Dist: bump2version (>=1.0.1,<2.0.0); extra == "dev"
Requires-Dist: click (==8.0.1)
Requires-Dist: flake8 (>=3.9.2,<4.0.0); extra == "test"
Requires-Dist: flake8-docstrings (>=1.6.0,<2.0.0); extra == "test"
Requires-Dist: isort (>=5.8.0,<6.0.0); extra == "test"
Requires-Dist: mkdocs (>=1.1.2,<2.0.0); extra == "doc"
Requires-Dist: mkdocs-autorefs (>=0.3.1,<0.4.0); extra == "doc"
Requires-Dist: mkdocs-include-markdown-plugin (>=1.0.0,<2.0.0); extra == "doc"
Requires-Dist: mkdocs-material (>=6.1.7,<7.0.0); extra == "doc"
Requires-Dist: mkdocs-material-extensions (>=1.0.1,<2.0.0)
Requires-Dist: mkdocstrings (>=0.18.0,<0.19.0); extra == "doc"
Requires-Dist: mypy (>=0.900,<0.901); extra == "test"
Requires-Dist: pip (>=20.3.1,<21.0.0); extra == "dev"
Requires-Dist: pre-commit (>=2.12.0,<3.0.0); extra == "dev"
Requires-Dist: pytest (>=6.2.4,<7.0.0); extra == "test"
Requires-Dist: pytest-cov (>=2.12.0,<3.0.0); extra == "test"
Requires-Dist: toml (>=0.10.2,<0.11.0); extra == "dev"
Requires-Dist: tox (>=3.20.1,<4.0.0); extra == "dev"
Requires-Dist: twine (>=3.3.0,<4.0.0); extra == "dev"
Requires-Dist: virtualenv (>=20.2.2,<21.0.0); extra == "dev"
